LICENSE.txt
MANIFEST.in
README.md
metadata.py
requirements.txt
setup.py
django_tinymce4.egg-info/PKG-INFO
django_tinymce4.egg-info/SOURCES.txt
django_tinymce4.egg-info/dependency_links.txt
django_tinymce4.egg-info/top_level.txt
docs/history.rst
docs/index.rst
docs/installation.rst
docs/usage.rst
tinymce/__init__.py
tinymce/compressor.py
tinymce/models.py
tinymce/profiles.py
tinymce/settings.py
tinymce/urls.py
tinymce/utils.py
tinymce/views.py
tinymce/widgets.py
tinymce/static/tinymce/license.txt
tinymce/static/tinymce/tinymce.min.js
tinymce/static/tinymce/langs/ar.js
tinymce/static/tinymce/langs/ar_SA.js
tinymce/static/tinymce/langs/az.js
tinymce/static/tinymce/langs/be.js
tinymce/static/tinymce/langs/bg_BG.js
tinymce/static/tinymce/langs/bn_BD.js
tinymce/static/tinymce/langs/bs.js
tinymce/static/tinymce/langs/ca.js
tinymce/static/tinymce/langs/cs.js
tinymce/static/tinymce/langs/cy.js
tinymce/static/tinymce/langs/da.js
tinymce/static/tinymce/langs/de.js
tinymce/static/tinymce/langs/de_AT.js
tinymce/static/tinymce/langs/dv.js
tinymce/static/tinymce/langs/el.js
tinymce/static/tinymce/langs/en_CA.js
tinymce/static/tinymce/langs/en_GB.js
tinymce/static/tinymce/langs/eo.js
tinymce/static/tinymce/langs/es.js
tinymce/static/tinymce/langs/es_MX.js
tinymce/static/tinymce/langs/et.js
tinymce/static/tinymce/langs/eu.js
tinymce/static/tinymce/langs/fa.js
tinymce/static/tinymce/langs/fa_IR.js
tinymce/static/tinymce/langs/fi.js
tinymce/static/tinymce/langs/fo.js
tinymce/static/tinymce/langs/fr_FR.js
tinymce/static/tinymce/langs/gd.js
tinymce/static/tinymce/langs/gl.js
tinymce/static/tinymce/langs/he_IL.js
tinymce/static/tinymce/langs/hi_IN.js
tinymce/static/tinymce/langs/hr.js
tinymce/static/tinymce/langs/hu_HU.js
tinymce/static/tinymce/langs/hy.js
tinymce/static/tinymce/langs/id.js
tinymce/static/tinymce/langs/is_IS.js
tinymce/static/tinymce/langs/it.js
tinymce/static/tinymce/langs/ja.js
tinymce/static/tinymce/langs/ka_GE.js
tinymce/static/tinymce/langs/kab.js
tinymce/static/tinymce/langs/kk.js
tinymce/static/tinymce/langs/km_KH.js
tinymce/static/tinymce/langs/ko_KR.js
tinymce/static/tinymce/langs/ku.js
