Metadata-Version: 1.1
Name: django-tinymce4
Version: 3.0.1
Summary: A Django application that contains a widget to render a form field as a TinyMCE 4 editor.
Home-page: https://github.com/dani0805/django-tinymce4
Author: Daniele Bernardini
Author-email: db@intranetstandard.com
License: MIT License
Keywords: django widget tinymce
Platform: any
Classifier: Development Status :: 5 - Production/Stable
Classifier: Environment :: Web Environment
Classifier: Framework :: Django
Classifier: Intended Audience :: Developers
Classifier: License :: OSI Approved :: MIT License
Classifier: Operating System :: OS Independent
Classifier: Programming Language :: Python
Classifier: Topic :: Software Development :: Libraries :: Application Frameworks
Classifier: Topic :: Software Development :: Libraries :: Python Modules
